odoo/addons/pos_payment_method_change_policy/README.rst
odoo/addons/pos_payment_method_change_policy/__init__.py
odoo/addons/pos_payment_method_change_policy/__manifest__.py
odoo/addons/pos_payment_method_change_policy/demo/product_product.xml
odoo/addons/pos_payment_method_change_policy/i18n/fr.po
odoo/addons/pos_payment_method_change_policy/i18n/it.po
odoo/addons/pos_payment_method_change_policy/i18n/pos_payment_method_change_policy.pot
odoo/addons/pos_payment_method_change_policy/models/__init__.py
odoo/addons/pos_payment_method_change_policy/models/pos_payment_method.py
odoo/addons/pos_payment_method_change_policy/models/pos_session.py
odoo/addons/pos_payment_method_change_policy/readme/CONFIGURE.rst
odoo/addons/pos_payment_method_change_policy/readme/CONTRIBUTORS.rst
odoo/addons/pos_payment_method_change_policy/readme/DESCRIPTION.rst
odoo/addons/pos_payment_method_change_policy/readme/ROADMAP.rst
odoo/addons/pos_payment_method_change_policy/readme/USAGE.rst
odoo/addons/pos_payment_method_change_policy/static/description/cash_1_payment_screen.png
odoo/addons/pos_payment_method_change_policy/static/description/cash_2_bill.png
odoo/addons/pos_payment_method_change_policy/static/description/cash_3_back_office.png
odoo/addons/pos_payment_method_change_policy/static/description/icon.png
odoo/addons/pos_payment_method_change_policy/static/description/index.html
odoo/addons/pos_payment_method_change_policy/static/description/payment_screen_profit_policy.png
odoo/addons/pos_payment_method_change_policy/static/description/profit_policy_1_payment_screen.png
odoo/addons/pos_payment_method_change_policy/static/description/profit_policy_2_bill.png
odoo/addons/pos_payment_method_change_policy/static/description/profit_policy_3_back_office.png
odoo/addons/pos_payment_method_change_policy/static/src/js/PaymentScreen.esm.js
odoo/addons/pos_payment_method_change_policy/static/src/js/models.esm.js
odoo/addons/pos_payment_method_change_policy/static/src/scss/style.scss
odoo_addon_pos_payment_method_change_policy-16.0.1.0.0.4.dist-info/METADATA
odoo_addon_pos_payment_method_change_policy-16.0.1.0.0.4.dist-info/WHEEL
odoo_addon_pos_payment_method_change_policy-16.0.1.0.0.4.dist-info/top_level.txt
odoo_addon_pos_payment_method_change_policy-16.0.1.0.0.4.dist-info/RECORD
